kpick/__init__.c
kpick/__init__.cpython-36m-x86_64-linux-gnu.so
kpick/__init__.pyi
kpick/dataset/__init__.c
kpick/dataset/__init__.cpython-36m-x86_64-linux-gnu.so
kpick/dataset/__init__.pyi
kpick/dataset/dataset.c
kpick/dataset/dataset.cpython-36m-x86_64-linux-gnu.so
kpick/dataset/dataset.pyi
kpick/dataset/grasp_cifar10_dber.c
kpick/dataset/grasp_cifar10_dber.cpython-36m-x86_64-linux-gnu.so
kpick/dataset/grasp_cifar10_dber.pyi
kpick/dataset/grip_cifar10_dber.c
kpick/dataset/grip_cifar10_dber.cpython-36m-x86_64-linux-gnu.so
kpick/dataset/grip_cifar10_dber.pyi
kpick/dataset/suction_cifar10_dber.c
kpick/dataset/suction_cifar10_dber.cpython-36m-x86_64-linux-gnu.so
kpick/dataset/suction_cifar10_dber.pyi
kpick/model/__init__.c
kpick/model/__init__.cpython-36m-x86_64-linux-gnu.so
kpick/model/__init__.pyi
kpick/model/grip_evaluation.c
kpick/model/grip_evaluation.cpython-36m-x86_64-linux-gnu.so
kpick/model/grip_evaluation.pyi
kpick/model/suction_evaluation.c
kpick/model/suction_evaluation.cpython-36m-x86_64-linux-gnu.so
kpick/model/suction_evaluation.pyi
kpick/processing/__init__.c
kpick/processing/__init__.cpython-36m-x86_64-linux-gnu.so
kpick/processing/__init__.pyi
kpick/processing/basic_imscanning_ray.c
kpick/processing/basic_imscanning_ray.cpython-36m-x86_64-linux-gnu.so
kpick/processing/basic_imscanning_ray.pyi
kpick/processing/grasp_detection.c
kpick/processing/grasp_detection.cpython-36m-x86_64-linux-gnu.so
kpick/processing/grasp_detection.pyi
kpick/processing/grasp_proposing.c
kpick/processing/grasp_proposing.cpython-36m-x86_64-linux-gnu.so
kpick/processing/grasp_proposing.pyi
kpick/processing/grip_detection.c
kpick/processing/grip_detection.cpython-36m-x86_64-linux-gnu.so
kpick/processing/grip_detection.pyi
kpick/processing/grip_detection_maskrcnn.c
kpick/processing/grip_detection_maskrcnn.cpython-36m-x86_64-linux-gnu.so
kpick/processing/grip_detection_maskrcnn.pyi
kpick/processing/grip_detection_v2_npose.c
kpick-1.0.1.dist-info/LICENSE
kpick-1.0.1.dist-info/METADATA
kpick-1.0.1.dist-info/WHEEL
kpick-1.0.1.dist-info/top_level.txt
kpick-1.0.1.dist-info/RECORD
